LICENSE.txt
MANIFEST.in
README.md
setup.py
style.md
QUBEKit/__init__.py
QUBEKit/dihedrals.py
QUBEKit/lennard_jones.py
QUBEKit/ligand.py
QUBEKit/mod_seminario.py
QUBEKit/protein_run.py
QUBEKit/protein_tools.py
QUBEKit/run.py
QUBEKit/tests_chris.py
QUBEKit/GUI/__init__.py
QUBEKit/GUI/gui.py
QUBEKit/GUI/nglviewer.js
QUBEKit/GUI/view.css
QUBEKit/GUI/view.html
QUBEKit/VEHICLe/bonds_angles.py
QUBEKit/engines/__init__.py
QUBEKit/engines/base_engine.py
QUBEKit/engines/chargemol.py
QUBEKit/engines/gaussian.py
QUBEKit/engines/onetep.py
QUBEKit/engines/openmm.py
QUBEKit/engines/psi4.py
QUBEKit/engines/qcengine.py
QUBEKit/engines/rdkit.py
QUBEKit/engines/torsiondrive.py
QUBEKit/parametrisation/__init__.py
QUBEKit/parametrisation/antechamber.py
QUBEKit/parametrisation/base_parametrisation.py
QUBEKit/parametrisation/openff.py
QUBEKit/parametrisation/xml.py
QUBEKit/parametrisation/xml_protein.py
QUBEKit/tests/__init__.py
QUBEKit/tests/ligand_tests.py
QUBEKit/tests/parametrisation_tests.py
QUBEKit/tests/protein_tests.py
QUBEKit/tests/seminario_tests.py
QUBEKit/tests/files/.QUBEKit_states
QUBEKit/tests/files/acetone.mol2
QUBEKit/tests/files/acetone.pdb
QUBEKit/tests/files/capped_leu.pdb
QUBEKit/utils/__init__.py
QUBEKit/utils/constants.py
QUBEKit/utils/decorators.py
QUBEKit/utils/exceptions.py
QUBEKit/utils/helpers.py
qubekit.egg-info/PKG-INFO
qubekit.egg-info/SOURCES.txt
qubekit.egg-info/dependency_links.txt
qubekit.egg-info/entry_points.txt
qubekit.egg-info/top_level.txt