Metadata-Version: 2.1
Name: qubekit
Version: 2.6.2
Summary: Quantum mechanical bespoke force field parameter generation
Home-page: https://github.com/qubekit/QUBEKit
Author: ['Joshua Thomas Horton', 'Chris Ringrose']
License: MIT
Platform: UNKNOWN
Classifier: Intended Audience :: Science/Research
Classifier: Topic :: Scientific/Engineering :: Bio-Informatics
Classifier: Topic :: Scientific/Engineering :: Chemistry
Classifier: Programming Language :: Python :: 3.6
Requires-Python: ~=3.6
